utah/__init__.py
utah-0.9.dist-info/METADATA
utah-0.9.dist-info/RECORD
utah-0.9.dist-info/WHEEL
utah-0.9.dist-info/top_level.txt
