Metadata-Version: 2.1
Name: utah
Version: 0.9
Summary: The official module for Utah Python / SLCPython
Home-page: http://github.com/slcpython/utah
Author: Faris Chebib
Author-email: faris@theluckybead.com
License: MIT
Keywords: utah meetup slc
Platform: UNKNOWN
Classifier: Intended Audience :: Education
Classifier: License :: OSI Approved :: MIT License
Requires-Dist: meetup-api
